html2pdfd.py
html2pdf_server-1.2.2.data/scripts/html2pdfd.py
html2pdf_server-1.2.2.dist-info/DESCRIPTION.rst
html2pdf_server-1.2.2.dist-info/METADATA
html2pdf_server-1.2.2.dist-info/RECORD
html2pdf_server-1.2.2.dist-info/WHEEL
html2pdf_server-1.2.2.dist-info/entry_points.txt
html2pdf_server-1.2.2.dist-info/metadata.json
html2pdf_server-1.2.2.dist-info/top_level.txt
