Metadata-Version: 2.0
Name: html2pdf-server
Version: 1.2.2
Summary: HTTP server that renders HTML to PDF
Home-page: https://github.com/spoqa/html2pdf-server
Author: Spoqa
Author-email: dev@spoqa.com
License: AGPLv3 or later
Platform: UNKNOWN
Classifier: Development Status :: 3 - Alpha
Classifier: Environment :: Web Environment
Classifier: Intended Audience :: Developers
Classifier: License :: OSI Approved :: GNU Affero General Public License v3 or later (AGPLv3+)
Classifier: Operating System :: MacOS :: MacOS X
Classifier: Operating System :: POSIX :: Linux
Classifier: Programming Language :: Python :: 3
Classifier: Programming Language :: Python :: 3.5
Classifier: Programming Language :: Python :: 3.6
Classifier: Topic :: Internet :: WWW/HTTP :: Browsers
Classifier: Topic :: Internet :: WWW/HTTP :: HTTP Servers
Classifier: Topic :: Internet :: WWW/HTTP :: WSGI :: Application
Classifier: Topic :: Printing
Requires-Dist: Wand (>=0.4.2)
Requires-Dist: WeasyPrint (>=0.22)
Requires-Dist: Werkzeug (>=0.9)
Requires-Dist: aiohttp (<1.1.0,>=1.0.5)
Requires-Dist: aiohttp-wsgi (==0.6.3)
